README.md
setup.py
jeepr/__init__.py
jeepr/_version.py
jeepr/model.py
jeepr/rad2np.py
jeepr/scan.py
jeepr/utils.py
jeepr.egg-info/PKG-INFO
jeepr.egg-info/SOURCES.txt
jeepr.egg-info/dependency_links.txt
jeepr.egg-info/not-zip-safe
jeepr.egg-info/requires.txt
jeepr.egg-info/top_level.txt