Metadata-Version: 1.1
Name: jeepr
Version: 0.1.2
Summary: Tools for managing GPR data.
Home-page: http://github.com/agile-geoscience/jeepr
Author: Agile Scientific
Author-email: hello@agilescientific.com
License: Apache 2
Platform: UNKNOWN
Classifier: Development Status :: 3 - Alpha
Classifier: Intended Audience :: Science/Research
Classifier: Natural Language :: English
Classifier: License :: OSI Approved :: Apache Software License
Classifier: Operating System :: OS Independent
Classifier: Programming Language :: Python
Classifier: Programming Language :: Python :: 3.5
Classifier: Programming Language :: Python :: 3.6
